{
    "intervals": [
        "18:20:00>18:28:00",
        "18:45:00>18:50:00",
        "19:15:00>19:25:00",
        "19:51:00>19:56:00",
        "20:22:00>20:27:00",
        "20:49:00>20:53:00",
        "21:15:00>21:21:00",
        "21:35:00>21:39:00",
        "22:00:00>22:08:00",
        "22:35:00>22:42:00"
    ],
    "tracklist": "Ingen",
    "group": "Ingen",
    "pool": "Pool_Evening_1",
    "loop": false,
    "randomize": false,
    "color": "#000000",
    "weekdays": [
        "*"
    ],
    "months": [
        "*"
    ],
    "weeks": [
        "*"
    ],
    "years": [
        "*"
    ],
    "start_second": "0",
    "stop_second": "*",
    "start_minute": "0",
    "stop_minute": "*",
    "start_time": 0,
    "end_time": 0
}